[
    {
        "name": "Repositorios Abiertos",
        "path": "/repositorios",
        "imagePath": "repositorios.png",
        "description": "Plataformas para compartir artículos y publicaciones científicas en acceso abierto."
    },
    {
        "name": "Datos de Investigación Abiertos",
        "path": "/repositorios",
        "imagePath": "/datos.png",
        "description": "Recursos para compartir y reutilizar datos científicos."
    },
    {
        "name": "Software y Herramientas Abiertas",
        "path": "/repositorios",
        "imagePath": "software.png",
        "description": "Programas de código abierto para la investigación."
    },
    {
        "name": "Licencias Abiertas",
        "path": "/repositorios",
        "imagePath": "licencias.png",
        "description": "Herramientas para compartir contenido legalmente."
    }
]